dndbuddy_core/__init__.py
dndbuddy_core/colors.py
dndbuddy_core/command.py
dndbuddy_core/pager.py
dndbuddy_core/settings.py
dndbuddy_core/terms.py
dndbuddy_core-0.0.1.dist-info/METADATA
dndbuddy_core-0.0.1.dist-info/WHEEL
dndbuddy_core-0.0.1.dist-info/top_level.txt
dndbuddy_core-0.0.1.dist-info/RECORD
