Metadata-Version: 2.1
Name: dndbuddy-core
Version: 0.0.1
Summary: The core libraries for DnDBuddy
Home-page: https://github.com/MattCCS/DnDBuddy-Core
Author: Matt Cotton
Author-email: matthewcotton.cs@gmail.com
License: UNKNOWN
Platform: UNKNOWN
Classifier: Programming Language :: Python :: 3
